[{"expression":"","description":"welcomeabcd","type":"DFA","testCases":[{"abcd":true,"ShowTestCase":true}],"graph":{"nodes":[{"left":464.0,"top":87.0,"i":true,"f":false,"name":"q0"},{"left":268.0,"top":182.0,"i":false,"f":false,"name":"q1"},{"left":290.0,"top":84.0,"i":false,"f":false,"name":"q2"},{"left":350.0,"top":51.0,"i":false,"f":false,"name":"q3"},{"left":440.0,"top":23.0,"i":false,"f":true,"name":"q4"}],"edges":[{"start":0,"end":1,"weight":"a"},{"start":1,"end":2,"weight":"b"},{"start":2,"end":3,"weight":"c"},{"start":3,"end":4,"weight":"d"}],"names":["q0","q1","q2","q3","q4"],"shorthand":false}}]